main.py
cli/__init__.py
cli/config.py
cli/version.py
cli/commands/__init__.py
cli/commands/errors.py
cli/commands/group.py
cli/commands/helpers.py
cli/commands/account/__init__.py
cli/commands/account/connect.py
cli/commands/account/disconnect.py
cli/commands/account/info.py
cli/commands/account/list.py
cli/commands/account/switch.py
cli/commands/box/__init__.py
cli/commands/box/account_change.py
cli/commands/box/clone.py
cli/commands/box/close.py
cli/commands/box/default.py
cli/commands/box/delete.py
cli/commands/box/info.py
cli/commands/box/list.py
cli/commands/box/make.py
cli/commands/box/open.py
cli/commands/box/request.py
cli/commands/box/share.py
cli/commands/box/switch.py
cli/commands/box/sync.py
cli/commands/chat/__init__.py
cli/commands/chat/info.py
cli/commands/chat/open.py
cli/commands/cli/__init__.py
cli/commands/cli/info.py
cli/commands/cli/init.py
cli/commands/dir/__init__.py
cli/commands/dir/forward.py
cli/commands/dir/list.py
cli/commands/dir/share.py
cli/commands/file/__init__.py
cli/commands/file/attr_edit.py
cli/commands/file/download.py
cli/commands/file/forward.py
cli/commands/file/import_.py
cli/commands/file/last_id.py
cli/commands/file/open.py
cli/commands/file/remove.py
cli/commands/file/search.py
cli/commands/file/share.py
cli/commands/file/upload.py
cli/commands/help/__init__.py
cli/commands/help/help.py
cli/commands/hidden/__init__.py
cli/commands/hidden/concat.py
cli/commands/hidden/phrase_gen.py
cli/commands/hidden/python_.py
cli/commands/hidden/sk_gen.py
cli/commands/logfile/__init__.py
cli/commands/logfile/open.py
cli/commands/logfile/send.py
cli/commands/logfile/size.py
cli/commands/logfile/wipe.py
cli/data/help.txt
cli/data/logo.ico
cli/tools/__init__.py
cli/tools/convert.py
cli/tools/other.py
cli/tools/session.py
cli/tools/strings.py
cli/tools/terminal.py
tgbox_cli-1.5.dist-info/licenses/LICENSE
tgbox_cli-1.5.dist-info/METADATA
tgbox_cli-1.5.dist-info/WHEEL
tgbox_cli-1.5.dist-info/entry_points.txt
tgbox_cli-1.5.dist-info/top_level.txt
tgbox_cli-1.5.dist-info/RECORD
