Metadata-Version: 2.4
Name: tgbox-cli
Version: 1.5
Summary: A Command Line Interface to the TGBOX
Home-page: https://github.com/NotStatilko/tgbox-cli
Download-URL: https://github.com/NotStatilko/tgbox-cli/archive/refs/tags/v1.5.tar.gz
Author: NotStatilko
Author-email: thenonproton@pm.me
License: MIT
Keywords: Telegram,Cloud-Storage,Cloud,Non-official
License-File: LICENSE
Requires-Dist: tgbox<2
Requires-Dist: click==8.3.0
Requires-Dist: enlighten==1.14.1
Provides-Extra: fast
Requires-Dist: tgbox[fast]<2; extra == "fast"
Dynamic: author
Dynamic: author-email
Dynamic: description
Dynamic: description-content-type
Dynamic: download-url
Dynamic: home-page
Dynamic: keywords
Dynamic: license
Dynamic: license-file
Dynamic: provides-extra
Dynamic: requires-dist
Dynamic: summary
